pybinarytree/BinaryTree.py
pybinarytree/__init__.py
pybinarytree/exceptions.py
pybinarytree/tests.py
pybinarytree-0.1.0.dist-info/LICENSE
pybinarytree-0.1.0.dist-info/METADATA
pybinarytree-0.1.0.dist-info/WHEEL
pybinarytree-0.1.0.dist-info/top_level.txt
pybinarytree-0.1.0.dist-info/RECORD
