Metadata-Version: 2.1
Name: pybinarytree
Version: 0.1.0
Summary: A binary tree class for sorting objects with <, <=, ==, >=, and > compatibility.
Author: Ethan Samford
Classifier: Programming Language :: Python :: 3
Classifier: License :: OSI Approved :: MIT License
Classifier: Operating System :: OS Independent
Requires-Python: >=3
License-File: LICENSE
